anatqc/__init__.py
anatqc/__version__.py
anatqc/bids/__init__.py
anatqc/cli/__init__.py
anatqc/cli/get.py
anatqc/cli/process.py
anatqc/cli/tandem.py
anatqc/config/__init__.py
anatqc/config/anatqc.yaml
anatqc/state/__init__.py
anatqc/tasks/__init__.py
anatqc/tasks/fs-mock.tar.gz
anatqc/tasks/morph.py
anatqc/tasks/mriqc.py
anatqc/tasks/vnav.py
anatqc/xnat/__init__.py
anatqc-0.6.0.data/scripts/anatQC.py
anatqc-0.6.0.dist-info/LICENSE
anatqc-0.6.0.dist-info/METADATA
anatqc-0.6.0.dist-info/WHEEL
anatqc-0.6.0.dist-info/top_level.txt
anatqc-0.6.0.dist-info/RECORD
