Metadata-Version: 2.2
Name: anatqc
Version: 0.6.0
Summary: Anatomical QC
Home-page: https://github.com/harvard-nrg/anatqc
Author: Neuroinformatics Research Group
Author-email: info@neuroinfo.org
License-File: LICENSE
Requires-Dist: yaxil
Requires-Dist: selfie
Requires-Dist: executors
Requires-Dist: morphometry
Requires-Dist: vnav
Dynamic: author
Dynamic: author-email
Dynamic: home-page
Dynamic: requires-dist
Dynamic: summary
